colorwheel/__init__.py
colorwheel/colorwheel.py
colorwheel/config.cfg
colorwheel-1.0.0.dist-info/LICENSE
colorwheel-1.0.0.dist-info/METADATA
colorwheel-1.0.0.dist-info/WHEEL
colorwheel-1.0.0.dist-info/top_level.txt
colorwheel-1.0.0.dist-info/RECORD
