Metadata-Version: 2.1
Name: colorwheel
Version: 1.0.0
Summary: Generate multi-color colorwheels
Home-page: https://github.com/aliloloee/colorwheel-generator
Author: Ali L.Jahromi
Author-email: aliloloee82@gmail.com
License: MIT
Platform: UNKNOWN
Classifier: License :: OSI Approved :: MIT License
Classifier: Programming Language :: Python :: 3
Classifier: Programming Language :: Python :: 3.8
Requires-Dist: pathlib
Requires-Dist: numpy
Requires-Dist: opencv-python
